Adder/self_checking_tb/random_test_cases/adder_des.sv
module adder #(

    parameter WIDTH = 32

)(

    input logic [WIDTH - 1 : 0] a, b,
    input logic valid, rst, clk,
    output logic [WIDTH : 0] sum

);

    always_ff @(posedge clk) begin
    
        if(rst) begin
        
            sum <= 0;
        
        end
        
        else if(valid) begin
        
            sum <= a + b;
            
        end
    
    end

endmodule

Adder/self_checking_tb/random_test_cases/adder_tb.sv
module adder_tb;

    parameter WIDTH = 32;
    
    logic valid, clk, rst;
    logic [WIDTH - 1 : 0] a, b;
    logic [WIDTH : 0] sum;
    int num_trans = 5;
    
    typedef struct{
    
        logic [WIDTH - 1 : 0] a;
        logic [WIDTH - 1 : 0] b;
        logic [WIDTH : 0] expected;
    
    } txn_t;
    
    int pass_count = 0;
    int fail_count = 0;
    
    txn_t sb_queue[$];
    
    adder #(.WIDTH(WIDTH)) dut (.a(a), .b(b), .sum(sum), .clk(clk), .rst(rst), .valid(valid));
    
    initial begin
    
        clk = 0;
        forever #5 clk = ~clk; 
    
    end
    
    initial begin
    
        reset();
        
        for(int i = 0; i < num_trans; i++)begin
            
            a = $urandom_range(255);
            b = $urandom_range(255);
            valid = $random;
            
            @(posedge clk);
            
            $display("[%0t] trans [%0d] a = %0d, b = %0d, valid = %0d, sum = %0d", $time, i + 1, a, b, valid, sum);
            $display();
            

            /*
            $write("[%0t] trans [%0d] a = %0d, b = %0d, valid = %0d, ", $time, i + 1, a, b, valid);
            @(posedge clk);
            $write("sum = %0d\n", sum);
            $display("\n");
            */
        
        end  
        
        repeat(5) @(posedge clk);
        
        $display("=========================");
        $display("Transcations Completed!");
        $display("Pass = %0d", pass_count);
        $display("Fail = %0d", fail_count);
        $display("=========================");
        
        #100;
        $finish;
            
    end
    
    always @(posedge clk) begin
    
        if(!rst && valid) begin
        
            txn_t t;
            
            t.a = a;
            t.b = b;
            t.expected = a + b;
            
            sb_queue.push_back(t);
        
        end
    
    end
    
    always @(posedge clk) begin
    
        if(!rst && sb_queue.size() > 0)begin
        
            txn_t t;
            t = sb_queue.pop_front();
            
            @(posedge clk);
            
            if(sum !== t.expected) begin
            
                $error("Fail: a = %0d, b = %0d expected = %0d, got = %0d", t.a, t.b, t.expected, sum);
                fail_count++;
            
            end
            
            else begin
            
                $display("Pass: a = %0d, b = %0d, result = %0d", t.a, t.b, sum);
                pass_count++;
            
            end
        
        end
    
    end
    
    task reset();
    
    rst = 1;
    valid = 0;
    a = 0;
    b = 0;
    repeat(2) @(posedge clk);
    rst = 0;
    
    endtask

endmodule

Adder/self_checking_tb/random_test_cases/dump.vcd
$date
	Fri Feb 20 04:16:59 2026
$end
$version
	QuestaSim Version 2021.3_1
$end
$timescale
	1ns
$end

$scope module adder_tb $end

$scope module dut $end
$var parameter 32 ! WIDTH $end
$var wire 1 " a [31] $end
$var wire 1 # a [30] $end
$var wire 1 $ a [29] $end
$var wire 1 % a [28] $end
$var wire 1 & a [27] $end
$var wire 1 ' a [26] $end
$var wire 1 ( a [25] $end
$var wire 1 ) a [24] $end
$var wire 1 * a [23] $end
$var wire 1 + a [22] $end
$var wire 1 , a [21] $end
$var wire 1 - a [20] $end
$var wire 1 . a [19] $end
$var wire 1 / a [18] $end
$var wire 1 0 a [17] $end
$var wire 1 1 a [16] $end
$var wire 1 2 a [15] $end
$var wire 1 3 a [14] $end
$var wire 1 4 a [13] $end
$var wire 1 5 a [12] $end
$var wire 1 6 a [11] $end
$var wire 1 7 a [10] $end
$var wire 1 8 a [9] $end
$var wire 1 9 a [8] $end
$var wire 1 : a [7] $end
$var wire 1 ; a [6] $end
$var wire 1 < a [5] $end
$var wire 1 = a [4] $end
$var wire 1 > a [3] $end
$var wire 1 ? a [2] $end
$var wire 1 @ a [1] $end
$var wire 1 A a [0] $end
$var wire 1 B b [31] $end
$var wire 1 C b [30] $end
$var wire 1 D b [29] $end
$var wire 1 E b [28] $end
$var wire 1 F b [27] $end
$var wire 1 G b [26] $end
$var wire 1 H b [25] $end
$var wire 1 I b [24] $end
$var wire 1 J b [23] $end
$var wire 1 K b [22] $end
$var wire 1 L b [21] $end
$var wire 1 M b [20] $end
$var wire 1 N b [19] $end
$var wire 1 O b [18] $end
$var wire 1 P b [17] $end
$var wire 1 Q b [16] $end
$var wire 1 R b [15] $end
$var wire 1 S b [14] $end
$var wire 1 T b [13] $end
$var wire 1 U b [12] $end
$var wire 1 V b [11] $end
$var wire 1 W b [10] $end
$var wire 1 X b [9] $end
$var wire 1 Y b [8] $end
$var wire 1 Z b [7] $end
$var wire 1 [ b [6] $end
$var wire 1 \ b [5] $end
$var wire 1 ] b [4] $end
$var wire 1 ^ b [3] $end
$var wire 1 _ b [2] $end
$var wire 1 ` b [1] $end
$var wire 1 a b [0] $end
$var wire 1 b valid $end
$var wire 1 c rst $end
$var wire 1 d clk $end
$var reg 33 e sum [32:0] $end
$upscope $end
$upscope $end
$enddefinitions $end
#0
$dumpvars
bx e
b100000 !
0d
1c
0b
0a
0`
0_
0^
0]
0\
0[
0Z
0Y
0X
0W
0V
0U
0T
0S
0R
0Q
0P
0O
0N
0M
0L
0K
0J
0I
0H
0G
0F
0E
0D
0C
0B
0A
0@
0?
0>
0=
0<
0;
0:
09
08
07
06
05
04
03
02
01
00
0/
0.
0-
0,
0+
0*
0)
0(
0'
0&
0%
0$
0#
0"
$end
#5
1d
b0 e
#10
0d
#15
1d
0c
1_
1^
1]
1\
1[
1A
1@
1?
1<
1;
1:
#20
0d
#25
1d
1b
0\
0[
0A
0@
1>
1=
0<
0;
#30
0d
#35
1d
b10111000 e
1a
1`
0^
0]
1\
1Z
0?
0=
1<
1;
#40
0d
#45
1d
b110001111 e
0a
0`
0\
1[
1@
1?
0>
1=
0<
0;
0:
#50
0d
#55
1d
b11011010 e
1a
0_
1^
1]
0Z
0@
0?
0=
#60
0d
#65
1d
b1011001 e
