Adder/self_checking_tb/using_interface/adder_des.sv
module adder(
    adder_intf.DUT vif
);

    always_ff @(posedge vif.clk) begin
    
        if(vif.rst) begin
            vif.sum <= 0;
        end
        
        else if(vif.valid) begin
            vif.sum <= vif.a + vif.b;
        end
    
    end

endmodule

Adder/self_checking_tb/random_test_cases/adder_tb.sv
module adder_tb;

    parameter WIDTH = 32;
    
    logic valid, clk, rst;
    logic [WIDTH - 1 : 0] a, b;
    logic [WIDTH : 0] sum;
    int num_trans = 5;
    
    typedef struct{
    
        logic [WIDTH - 1 : 0] a;
        logic [WIDTH - 1 : 0] b;
        logic [WIDTH : 0] expected;
    
    } txn_t;
    
    int pass_count = 0;
    int fail_count = 0;
    
    txn_t sb_queue[$];
    
    adder #(.WIDTH(WIDTH)) dut (.a(a), .b(b), .sum(sum), .clk(clk), .rst(rst), .valid(valid));
    
    initial begin
    
        clk = 0;
        forever #5 clk = ~clk; 
    
    end
    
    initial begin
    
        reset();
        
        for(int i = 0; i < num_trans; i++)begin
            
            a = $urandom_range(255);
            b = $urandom_range(255);
            valid = $random;
            
            @(posedge clk);
            
            $display("[%0t] trans [%0d] a = %0d, b = %0d, valid = %0d, sum = %0d", $time, i + 1, a, b, valid, sum);
            $display();
            

            /*
            $write("[%0t] trans [%0d] a = %0d, b = %0d, valid = %0d, ", $time, i + 1, a, b, valid);
            @(posedge clk);
            $write("sum = %0d\n", sum);
            $display("\n");
            */
        
        end  
        
        repeat(5) @(posedge clk);
        
        $display("=========================");
        $display("Transcations Completed!");
        $display("Pass = %0d", pass_count);
        $display("Fail = %0d", fail_count);
        $display("=========================");
        
        #100;
        $finish;
            
    end
    
    always @(posedge clk) begin
    
        if(!rst && valid) begin
        
            txn_t t;
            
            t.a = a;
            t.b = b;
            t.expected = a + b;
            
            sb_queue.push_back(t);
        
        end
    
    end
    
    always @(posedge clk) begin
    
        if(!rst && sb_queue.size() > 0)begin
        
            txn_t t;
            t = sb_queue.pop_front();
            
            @(posedge clk);
            
            if(sum !== t.expected) begin
            
                $error("Fail: a = %0d, b = %0d expected = %0d, got = %0d", t.a, t.b, t.expected, sum);
                fail_count++;
            
            end
            
            else begin
            
                $display("Pass: a = %0d, b = %0d, result = %0d", t.a, t.b, sum);
                pass_count++;
            
            end
        
        end
    
    end
    
    task reset();
    
    rst = 1;
    valid = 0;
    a = 0;
    b = 0;
    repeat(2) @(posedge clk);
    rst = 0;
    
    endtask

endmodule

Adder/self_checking_tb/using_interface/dump.vcd
$date
	Sat Feb 21 00:31:08 2026
$end
$version
	QuestaSim Version 2021.3_1
$end
$timescale
	1ns
$end

$scope module adder_tb $end

$scope module intf $end
$var parameter 32 ! WIDTH $end
$var wire 1 " clk $end
$var wire 1 # rst $end
$var reg 32 $ a [31:0] $end
$var reg 32 % b [31:0] $end
$var reg 1 & valid $end
$var reg 33 ' sum [32:0] $end
$upscope $end
$upscope $end
$enddefinitions $end
#0
$dumpvars
b0 $
b0 %
0&
bx '
b100000 !
1#
0"
$end
#5
1"
b0 '
#10
0"
#15
1"
0#
#20
0"
#25
1"
#26
b10110010 $
b10000 %
#30
0"
#35
1"
#36
1&
b110000 $
b10110101 %
#40
0"
#45
1"
b11100101 '
#46
b10110110 $
b10100 %
#50
0"
#55
1"
b11001010 '
#56
b11011111 $
b10111011 %
#60
0"
#65
1"
b110011010 '
#66
b11101011 $
b1000001 %
#70
0"
#75
1"
b100101100 '
#76
b1000000 $
b10001010 %
#80
0"
#85
1"
b11001010 '
#86
b11 $
b11111100 %
#90
0"
#95
1"
b11111111 '
#96
0&
b1011101 $
b11101 %
#100
0"
#105
1"
#106
1&
b1101010 $
b10110 %
#110
0"
#115
1"
b10000000 '
#116
b111111 $
b100011 %
#120
0"
#125
1"
b1100010 '
#126
0&
b10101000 $
b10010000 %
#130
0"
#135
1"
#136
1&
b100101 $
b10000010 %
#140
0"
#145
1"
b10100111 '
#146
b1011011 $
b11110010 %
#150
0"
#155
1"
b101001101 '
#156
0&
b110001 $
b11001101 %
#160
0"
#165
1"
#166
1&
b1100100 $
b101011 %
#170
0"
#175
1"
b10001111 '
#176
0&
b11101010 $
b10010001 %
#180
0"
#185
1"
#186
1&
b11110110 $
b10010110 %
#190
0"
#195
1"
b110001100 '
#196
0&
b1010101 $
b1110110 %
#200
0"
#205
1"
#206
1&
b10111000 $
b10100 %
#210
0"
#215
1"
b11001100 '
#216
b10000001 $
b1110111 %
#220
0"
#225
1"
b11111000 '
#226
0&
b11101101 $
b10000010 %
#230
0"
#235
1"
#236
1&
b11011001 $
b10100 %
#240
0"
#245
1"
b11101101 '
#246
0&
b1111101 $
b10001100 %
#250
0"
#255
1"
#256
b1001011 $
b1111100 %
#260
0"
#265
1"
#266
b1110000 $
b10100000 %
#270
0"
#275
1"
#276
1&
b1001100 $
b1100001 %
#280
0"
#285
1"
b10101101 '
#286
0&
b10011101 $
b11101 %
#290
0"
#295
1"
#296
1&
b10110 $
b10111001 %
#300
0"
#305
1"
b11001111 '
#306
b1110010 $
b10010011 %
#310
0"
#315
1"
b100000101 '
#316
b1000101 $
b1001110 %
#320
0"
#325
1"
b10010011 '
